pdfserver/__init__.py
pdfserver/server.py
pdf2png_mcp_server-0.1.0.dist-info/METADATA
pdf2png_mcp_server-0.1.0.dist-info/WHEEL
pdf2png_mcp_server-0.1.0.dist-info/entry_points.txt
pdf2png_mcp_server-0.1.0.dist-info/top_level.txt
pdf2png_mcp_server-0.1.0.dist-info/RECORD
