Metadata-Version: 2.4
Name: pdf2png-mcp-server
Version: 0.1.0
Summary: Add your description here
Author-email: Kirk Truax <kirktruax93@proton.me>
Requires-Python: >=3.13
Requires-Dist: asyncio>=3.4.3
Requires-Dist: mcp>=1.5.0
Requires-Dist: pdf2image>=1.17.0
